{
  "shaders": [
    {
      "name": "spriteShader",
      "filePath_v": "res/shaders/vSprite.txt",
      "filePath_f": "res/shaders/fSprite.txt"
    }
  ],

  "textureAtlases": [
    {
      "name": "mapTextureAtlas",
      "filePath": "res/texture/globalmap.png",
      "subTextureWidth": 16,
      "subTextureHeight": 16,
      "subTextures": [
        "FullRoad",
        "House",
        "Water1",
        "Water2",
        "Water3",
        "Border",
        "ArrowBottom",
        "ArrowTop",
        "ArrowLeft",
        "ArrowRight"
      ]
    },

    {
      "name": "betonTextureAtlas",
      "filePath": "res/texture/Beton.png",
      "subTextureWidth": 16,
      "subTextureHeight": 16,
      "subTextures": [
        "fullBeton",
        "leftBottomBeton",
        "rightBottomBeton",
        "bottomBeton",
        "leftTopBeton",
        "leftBeton",
        "leftTop_rightBottom_beton",
        "unRightTopBeton",
        "rightTopBeton",
        "leftBottom_rightTop_beton",
        "rightBeton",
        "unLeftTopBeton",
        "topBeton",
        "unRightBottomBeton",
        "unLeftBottomBeton"
      ]
    },

    {
      "name": "castleShopsTextureAtlas",
      "filePath": "res/texture/CastleShop.png",
      "subTextureWidth": 32,
      "subTextureHeight": 64,
      "subTextures": [
        "castleShopsTexture"
      ]
    },

    {
      "name": "leftShopsTextureAtlas_1",
      "filePath": "res/texture/LeftShop1.png",
      "subTextureWidth": 32,
      "subTextureHeight": 32,
      "subTextures": [
        "LeftShop1"
      ]
    },

    {
      "name": "leftShopsTextureAtlas_2",
      "filePath": "res/texture/LeftShop2.png",
      "subTextureWidth": 32,
      "subTextureHeight": 32,
      "subTextures": [
        "LeftShop2"
      ]
    },

    {
      "name": "rightShopsTextureAtlas_1",
      "filePath": "res/texture/RightShop1.png",
      "subTextureWidth": 32,
      "subTextureHeight": 32,
      "subTextures": [
        "RightShop1"
      ]
    },

    {
      "name": "rightShopsTextureAtlas_2",
      "filePath": "res/texture/RightShop2.png",
      "subTextureWidth": 32,
      "subTextureHeight": 32,
      "subTextures": [
        "RightShop2"
      ]
    },

    {
      "name": "auxiliaryTextureAtlas",
      "filePath": "res/texture/Auxiliary.png",
      "subTextureWidth": 16,
      "subTextureHeight": 16,
      "subTextures": [
        "inaccessibleField",
        "affordableField",
        "coin",
        "pointer1",
        "pointer2",
        "pointer3"
      ]
    },

    {
      "name": "numberTextureAtlas",
      "filePath": "res/texture/Numbers.png",
      "subTextureWidth": 5,
      "subTextureHeight": 9,
      "subTextures": [
        "zero",
        "one",
        "two",
        "three",
        "four",
        "five",
        "six",
        "seven",
        "eight",
        "nine"
      ]
    },

    {
      "name": "archerTextureAtlas",
      "filePath": "res/texture/Archer.png",
      "subTextureWidth": 16,
      "subTextureHeight": 18,
      "subTextures": [
        "ArcherRight1",
        "ArcherRight2",
        "ArcherLeft1",
        "ArcherLeft2",
        "ArcherAttackRight1",
        "ArcherAttackRight2",
        "ArcherAttackLeft1",
        "ArcherAttackLeft2"
      ]
    },

    {
      "name": "knightTextureAtlas",
      "filePath": "res/texture/knight.png",
      "subTextureWidth": 16,
      "subTextureHeight": 18,
      "subTextures": [
        "KnightRight1",
        "KnightRight2",
        "KnightLeft1",
        "KnightLeft2",
        "KnightAttackRight1",
        "KnightAttackRight2",
        "KnightAttackLeft1",
        "KnightAttackLeft2"
      ]
    },

    {
      "name": "barbarianTextureAtlas",
      "filePath": "res/texture/barbarian.png",
      "subTextureWidth": 16,
      "subTextureHeight": 18,
      "subTextures": [
        "BarbarianRight1",
        "BarbarianRight2",
        "BarbarianLeft1",
        "BarbarianLeft2",
        "BarbarianAttackRight1",
        "BarbarianAttackRight2",
        "BarbarianAttackLeft1",
        "BarbarianAttackLeft2"
      ]
    },

    {
      "name": "angelTextureAtlas",
      "filePath": "res/texture/angel.png",
      "subTextureWidth": 16,
      "subTextureHeight": 18,
      "subTextures": [
        "AngelRight1",
        "AngelRight2",
        "AngelLeft1",
        "AngelLeft2",
        "AngelAttackRight1",
        "AngelAttackRight2",
        "AngelAttackLeft1",
        "AngelAttackLeft2"
      ]
    },

    {
      "name": "magicanTextureAtlas",
      "filePath": "res/texture/magican.png",
      "subTextureWidth": 16,
      "subTextureHeight": 18,
      "subTextures": [
        "magicanRight1",
        "magicanRight2",
        "magicanLeft1",
        "magicanLeft2",
        "magicanAttackRight1",
        "magicanAttackRight2",
        "magicanAttackLeft1",
        "magicanAttackLeft2"
      ]
    },

    {
      "name": "titanTextureAtlas",
      "filePath": "res/texture/titan.png",
      "subTextureWidth": 16,
      "subTextureHeight": 18,
      "subTextures": [
        "titanRight1",
        "titanRight2",
        "titanLeft1",
        "titanLeft2",
        "titanAttackRight1",
        "titanAttackRight2",
        "titanAttackLeft1",
        "titanAttackLeft2"
      ]
    }
  ],

  "sprite": [
    {
      "name": "zero",
      "textureAtlas": "numberTextureAtlas",
      "shader": "spriteShader",
      "initialSubTexture": "zero"
    },

    {
      "name": "one",
      "textureAtlas": "numberTextureAtlas",
      "shader": "spriteShader",
      "initialSubTexture": "one"
    },

    {
      "name": "two",
      "textureAtlas": "numberTextureAtlas",
      "shader": "spriteShader",
      "initialSubTexture": "two"
    },

    {
      "name": "three",
      "textureAtlas": "numberTextureAtlas",
      "shader": "spriteShader",
      "initialSubTexture": "three"
    },

    {
      "name": "four",
      "textureAtlas": "numberTextureAtlas",
      "shader": "spriteShader",
      "initialSubTexture": "four"
    },

    {
      "name": "five",
      "textureAtlas": "numberTextureAtlas",
      "shader": "spriteShader",
      "initialSubTexture": "five"
    },

    {
      "name": "six",
      "textureAtlas": "numberTextureAtlas",
      "shader": "spriteShader",
      "initialSubTexture": "six"
    },

    {
      "name": "seven",
      "textureAtlas": "numberTextureAtlas",
      "shader": "spriteShader",
      "initialSubTexture": "seven"
    },

    {
      "name": "eight",
      "textureAtlas": "numberTextureAtlas",
      "shader": "spriteShader",
      "initialSubTexture": "eight"
    },

    {
      "name": "nine",
      "textureAtlas": "numberTextureAtlas",
      "shader": "spriteShader",
      "initialSubTexture": "nine"
    },

    {
      "name": "FullRoad",
      "textureAtlas": "mapTextureAtlas",
      "shader": "spriteShader",
      "initialSubTexture": "FullRoad"
    },

    {
      "name": "fullBeton",
      "textureAtlas": "betonTextureAtlas",
      "shader": "spriteShader",
      "initialSubTexture": "fullBeton"
    },

    {
      "name": "leftBottomBeton",
      "textureAtlas": "betonTextureAtlas",
      "shader": "spriteShader",
      "initialSubTexture": "leftBottomBeton"
    },

    {
      "name": "rightBottomBeton",
      "textureAtlas": "betonTextureAtlas",
      "shader": "spriteShader",
      "initialSubTexture": "rightBottomBeton"
    },

    {
      "name": "bottomBeton",
      "textureAtlas": "betonTextureAtlas",
      "shader": "spriteShader",
      "initialSubTexture": "bottomBeton"
    },

    {
      "name": "leftTopBeton",
      "textureAtlas": "betonTextureAtlas",
      "shader": "spriteShader",
      "initialSubTexture": "leftTopBeton"
    },

    {
      "name": "leftBeton",
      "textureAtlas": "betonTextureAtlas",
      "shader": "spriteShader",
      "initialSubTexture": "leftBeton"
    },

    {
      "name": "leftTop_rightBottom_beton",
      "textureAtlas": "betonTextureAtlas",
      "shader": "spriteShader",
      "initialSubTexture": "leftTop_rightBottom_beton"
    },

    {
      "name": "House",
      "textureAtlas": "mapTextureAtlas",
      "shader": "spriteShader",
      "initialSubTexture": "House"
    },

    {
      "name": "Border",
      "textureAtlas": "mapTextureAtlas",
      "shader": "spriteShader",
      "initialSubTexture": "Border"
    },

    {
      "name": "ArrowTop",
      "textureAtlas": "mapTextureAtlas",
      "shader": "spriteShader",
      "initialSubTexture": "ArrowTop"
    },

    {
      "name": "ArrowBottom",
      "textureAtlas": "mapTextureAtlas",
      "shader": "spriteShader",
      "initialSubTexture": "ArrowBottom"
    },

    {
      "name": "ArrowLeft",
      "textureAtlas": "mapTextureAtlas",
      "shader": "spriteShader",
      "initialSubTexture": "ArrowLeft"
    },

    {
      "name": "ArrowRight",
      "textureAtlas": "mapTextureAtlas",
      "shader": "spriteShader",
      "initialSubTexture": "ArrowRight"
    },

    {
      "name": "inaccessibleField",
      "textureAtlas": "auxiliaryTextureAtlas",
      "shader": "spriteShader",
      "initialSubTexture": "inaccessibleField"
    },

    {
      "name": "affordableField",
      "textureAtlas": "auxiliaryTextureAtlas",
      "shader": "spriteShader",
      "initialSubTexture": "affordableField"
    },

    {
      "name": "coin",
      "textureAtlas": "auxiliaryTextureAtlas",
      "shader": "spriteShader",
      "initialSubTexture": "coin"
    },

    {
      "name": "castleShopsSprite",
      "textureAtlas": "castleShopsTextureAtlas",
      "shader": "spriteShader",
      "initialSubTexture": "castleShopsTexture"
    },

    {
      "name": "leftShopsSprite_1",
      "textureAtlas": "leftShopsTextureAtlas_1",
      "shader": "spriteShader",
      "initialSubTexture": "LeftShop1"
    },

    {
      "name": "leftShopsSprite_2",
      "textureAtlas": "leftShopsTextureAtlas_2",
      "shader": "spriteShader",
      "initialSubTexture": "LeftShop2"
    },

    {
      "name": "rightShopsSprite_1",
      "textureAtlas": "rightShopsTextureAtlas_1",
      "shader": "spriteShader",
      "initialSubTexture": "RightShop1"
    },

    {
      "name": "rightShopsSprite_2",
      "textureAtlas": "rightShopsTextureAtlas_2",
      "shader": "spriteShader",
      "initialSubTexture": "RightShop2"
    },

    {
      "name": "pointerAnimation",
      "textureAtlas": "auxiliaryTextureAtlas",
      "shader": "spriteShader",
      "initialSubTexture": "pointer3",
      "frames": [
        {
          "subTexture": "pointer3",
          "duration": 500
        },
        {
          "subTexture": "pointer2",
          "duration": 500
        },
        {
          "subTexture": "pointer1",
          "duration": 500
        }
      ]
    },


    {
      "name": "waterSprite",
      "textureAtlas": "mapTextureAtlas",
      "shader": "spriteShader",
      "initialSubTexture": "Water1",
      "frames": [
        {
          "subTexture": "Water1",
          "duration": 1000
        },
        {
          "subTexture": "Water2",
          "duration": 1000
        },
        {
          "subTexture": "Water3",
          "duration": 1000
        }
      ]
    },

    {
      "name": "archerState_Left",
      "textureAtlas": "archerTextureAtlas",
      "shader": "spriteShader",
      "initialSubTexture": "ArcherLeft1",
      "frames": [
        {
          "subTexture": "ArcherLeft1",
          "duration": 500
        },
        {
          "subTexture": "ArcherLeft2",
          "duration": 500
        }
      ]
    },

    {
      "name": "archerState_Right",
      "textureAtlas": "archerTextureAtlas",
      "shader": "spriteShader",
      "initialSubTexture": "ArcherRight1",
      "frames": [
        {
          "subTexture": "ArcherRight1",
          "duration": 500
        },
        {
          "subTexture": "ArcherRight2",
          "duration": 500
        }
      ]
    },

    {
      "name": "knightState_Left",
      "textureAtlas": "knightTextureAtlas",
      "shader": "spriteShader",
      "initialSubTexture": "KnightLeft1",
      "frames": [
        {
          "subTexture": "KnightLeft1",
          "duration": 500
        },
        {
          "subTexture": "KnightLeft1",
          "duration": 500
        }
      ]
    },

    {
      "name": "knightState_Right",
      "textureAtlas": "knightTextureAtlas",
      "shader": "spriteShader",
      "initialSubTexture": "KnightRight1",
      "frames": [
        {
          "subTexture": "KnightRight1",
          "duration": 500
        },
        {
          "subTexture": "KnightRight2",
          "duration": 500
        }
      ]
    },

    {
      "name": "barbarianState_Left",
      "textureAtlas": "barbarianTextureAtlas",
      "shader": "spriteShader",
      "initialSubTexture": "BarbarianLeft1",
      "frames": [
        {
          "subTexture": "BarbarianLeft1",
          "duration": 500
        },
        {
          "subTexture": "BarbarianLeft2",
          "duration": 500
        }
      ]
    },

    {
      "name": "barbarianState_Right",
      "textureAtlas": "barbarianTextureAtlas",
      "shader": "spriteShader",
      "initialSubTexture": "BarbarianRight1",
      "frames": [
        {
          "subTexture": "BarbarianRight1",
          "duration": 500
        },
        {
          "subTexture": "BarbarianRight2",
          "duration": 500
        }
      ]
    },

    {
      "name": "angelState_Left",
      "textureAtlas": "angelTextureAtlas",
      "shader": "spriteShader",
      "initialSubTexture": "AngelLeft1",
      "frames": [
        {
          "subTexture": "AngelLeft1",
          "duration": 500
        },
        {
          "subTexture": "AngelLeft2",
          "duration": 500
        }
      ]
    },

    {
      "name": "angelState_Right",
      "textureAtlas": "angelTextureAtlas",
      "shader": "spriteShader",
      "initialSubTexture": "AngelRight1",
      "frames": [
        {
          "subTexture": "AngelRight1",
          "duration": 500
        },
        {
          "subTexture": "AngelRight2",
          "duration": 500
        }
      ]
    },

    {
      "name": "magicanState_Left",
      "textureAtlas": "magicanTextureAtlas",
      "shader": "spriteShader",
      "initialSubTexture": "magicanLeft1",
      "frames": [
        {
          "subTexture": "magicanLeft1",
          "duration": 500
        },
        {
          "subTexture": "magicanLeft2",
          "duration": 500
        }
      ]
    },

    {
      "name": "magicanState_Right",
      "textureAtlas": "magicanTextureAtlas",
      "shader": "spriteShader",
      "initialSubTexture": "magicanRight1",
      "frames": [
        {
          "subTexture": "magicanRight1",
          "duration": 500
        },
        {
          "subTexture": "magicanRight2",
          "duration": 500
        }
      ]
    },

    {
      "name": "titanState_Left",
      "textureAtlas": "titanTextureAtlas",
      "shader": "spriteShader",
      "initialSubTexture": "titanLeft1",
      "frames": [
        {
          "subTexture": "titanLeft1",
          "duration": 500
        },
        {
          "subTexture": "titanLeft2",
          "duration": 500
        }
      ]
    },

    {
      "name": "titanState_Right",
      "textureAtlas": "titanTextureAtlas",
      "shader": "spriteShader",
      "initialSubTexture": "titanRight1",
      "frames": [
        {
          "subTexture": "titanRight1",
          "duration": 500
        },
        {
          "subTexture": "titanRight2",
          "duration": 500
        }
      ]
    }
  ],

  "shopsScreen": [
    "000505050005000",
    "055505050505050",
    "000500050505000",
    "550505050505055",
    "000505050005055"
  ],

  "levels": [
    {
      "description": [
        "2222222",
        "2000002",
        "2001002",
        "2300042",
        "2000002",
        "2000002",
        "2200022",
        "2000002",
        "2000002",
        "2060702",
        "2222222"
      ]
    }
  ]
}